{
    "789695310875197460": {
        "sent": 198,
        "commands": 28
    },
    "614955640120410168": {
        "sent": 31,
        "commands": 1
    },
    "235148962103951360": {
        "sent": 3
    },
    "846890182145474580": {
        "sent": 7
    },
    "846890180162224128": {
        "sent": 2
    },
    "1001201900961681489": {
        "sent": 1
    },
    "695776178707103786": {
        "sent": 93,
        "commands": 1
    },
    "846890179088089128": {
        "sent": 5
    },
    "483860253830807552": {
        "sent": 126,
        "commands": 2
    },
    "827000928972439562": {
        "sent": 6
    },
    "846890181126258708": {
        "sent": 3
    },
    "895805585663074315": {
        "sent": 12
    }
}